pybel_tools/__init__.py
pybel_tools/assess_completeness.py
pybel_tools/chemistry.py
pybel_tools/definition_utils.py
pybel_tools/dict_manager.py
pybel_tools/document_utils.py
pybel_tools/generation.py
pybel_tools/node_utils.py
pybel_tools/pathway_assigner.py
pybel_tools/typing.py
pybel_tools/utils.py
pybel_tools/version.py
pybel_tools/analysis/__init__.py
pybel_tools/analysis/causalr.py
pybel_tools/analysis/concordance.py
pybel_tools/analysis/heat.py
pybel_tools/analysis/mechanisms.py
pybel_tools/analysis/rcr.py
pybel_tools/analysis/spia.py
pybel_tools/analysis/sst.py
pybel_tools/analysis/epicom/__init__.py
pybel_tools/analysis/epicom/algorithm.py
pybel_tools/analysis/epicom/build.py
pybel_tools/analysis/epicom/models.py
pybel_tools/analysis/neurommsig/__init__.py
pybel_tools/analysis/neurommsig/__main__.py
pybel_tools/analysis/neurommsig/algorithm.py
pybel_tools/analysis/neurommsig/cli.py
pybel_tools/analysis/neurommsig/export.py
pybel_tools/assembler/__init__.py
pybel_tools/assembler/html/__init__.py
pybel_tools/assembler/html/assembler.py
pybel_tools/assembler/html/templates/base.html
pybel_tools/assembler/html/templates/compilation.html
pybel_tools/assembler/html/templates/index.html
pybel_tools/assembler/ideogram/__init__.py
pybel_tools/assembler/ideogram/assembler.py
pybel_tools/assembler/ideogram/templates/index.html
pybel_tools/assembler/ideogram/templates/render_with_javascript.js
pybel_tools/assembler/reified_graph/__init__.py
pybel_tools/assembler/reified_graph/assembler.py
pybel_tools/assembler/reified_graph/simple_assembler.py
pybel_tools/biogrammar/__init__.py
pybel_tools/biogrammar/double_edges.py
pybel_tools/filters/__init__.py
pybel_tools/filters/edge_filters.py
pybel_tools/filters/node_deletion.py
pybel_tools/filters/node_filters.py
pybel_tools/integration/__init__.py
pybel_tools/integration/overlay.py
pybel_tools/mutation/__init__.py
pybel_tools/mutation/bound.py
pybel_tools/mutation/collapse.py
pybel_tools/mutation/deletion.py
pybel_tools-0.9.1.dist-info/LICENSE
pybel_tools-0.9.1.dist-info/METADATA
pybel_tools-0.9.1.dist-info/WHEEL
pybel_tools-0.9.1.dist-info/top_level.txt
pybel_tools-0.9.1.dist-info/zip-safe
pybel_tools-0.9.1.dist-info/RECORD
