Metadata-Version: 2.1
Name: pybel-tools
Version: 0.9.1
Summary: A cool pool of tools for BEL
Home-page: https://github.com/pybel/pybel-tools
Author: Charles Tapley Hoyt
Author-email: cthoyt@gmail.com
Maintainer: Charles Tapley Hoyt
Maintainer-email: cthoyt@gmail.com
License: MIT
Download-URL: https://github.com/pybel/pybel-tools/releases
Project-URL: Bug Tracker, https://github.com/pybel/pybel-tools/issues
Project-URL: Source Code, https://github.com/pybel/pybel-tools
Project-URL: Documentation, https://pybel-tools.readthedocs.io
Keywords: Biological Expression Language,BEL,Networks Biology,Systems Biology
Platform: UNKNOWN
Classifier: Development Status :: 1 - Planning
Classifier: Intended Audience :: Developers
Classifier: License :: OSI Approved :: MIT License
Classifier: Operating System :: OS Independent
Classifier: Programming Language :: Python
Classifier: Programming Language :: Python :: 3.7
Classifier: Programming Language :: Python :: 3.8
Classifier: Programming Language :: Python :: 3.9
Classifier: Programming Language :: Python :: 3 :: Only
Classifier: Topic :: Scientific/Engineering :: Bio-Informatics
Classifier: Topic :: Scientific/Engineering :: Chemistry
Requires-Python: >=3.7
Requires-Dist: dataclasses-json
Requires-Dist: networkx
Requires-Dist: requests
Requires-Dist: click
Requires-Dist: sqlalchemy
Requires-Dist: tqdm
Requires-Dist: bel-resources (>=0.0.3)
Requires-Dist: pybel (>=0.15.0)
Requires-Dist: pandas
Requires-Dist: scipy
Requires-Dist: numpy
Requires-Dist: matplotlib
Requires-Dist: seaborn
Provides-Extra: assembler_html
Requires-Dist: jinja2 ; extra == 'assembler_html'
Provides-Extra: assembler_ideogram
Requires-Dist: IPython ; extra == 'assembler_ideogram'
Requires-Dist: jinja2 ; extra == 'assembler_ideogram'
Provides-Extra: docs
Requires-Dist: sphinx ; extra == 'docs'
Requires-Dist: sphinx-rtd-theme ; extra == 'docs'
Requires-Dist: sphinx-click ; extra == 'docs'
Requires-Dist: sphinx-autodoc-typehints ; extra == 'docs'
Requires-Dist: IPython ; extra == 'docs'
